README.md
setup.py
invana_bot/__init__.py
invana_bot.egg-info/PKG-INFO
invana_bot.egg-info/SOURCES.txt
invana_bot.egg-info/dependency_links.txt
invana_bot.egg-info/entry_points.txt
invana_bot.egg-info/requires.txt
invana_bot.egg-info/top_level.txt
invana_bot/cmd/__init__.py
invana_bot/cmd/run.py
invana_bot/core/__init__.py
invana_bot/core/downloaders/__init__.py
invana_bot/core/downloaders/spider_analytics.py
invana_bot/core/engines/__init__.py
invana_bot/core/engines/base.py
invana_bot/core/engines/cti.py
invana_bot/core/engines/single.py
invana_bot/core/httpcache/__init__.py
invana_bot/core/httpcache/elasticsearch.py
invana_bot/core/httpcache/mongodb.py
invana_bot/core/storages/__init__.py
invana_bot/core/storages/default.py
invana_bot/extractors/__init__.py
invana_bot/extractors/base.py
invana_bot/extractors/content.py
invana_bot/extractors/images.py
invana_bot/extractors/links.py
invana_bot/extractors/python.py
invana_bot/fields/__init__.py
invana_bot/fields/list.py
invana_bot/fields/single.py
invana_bot/jobs/__init__.py
invana_bot/jobs/base.py
invana_bot/jobs/cti.py
invana_bot/manifests/__init__.py
invana_bot/manifests/cti.py
invana_bot/manifests/single.py
invana_bot/settings/__init__.py
invana_bot/settings/default.py
invana_bot/spiders/__init__.py
invana_bot/spiders/api.py
invana_bot/spiders/base.py
invana_bot/spiders/web.py
invana_bot/spiders/xml.py
invana_bot/transformers/__init__.py
invana_bot/transformers/default.py
invana_bot/transformers/executors.py
invana_bot/transformers/mongodb.py
invana_bot/traversals/__init__.py
invana_bot/traversals/base.py
invana_bot/traversals/generic.py
invana_bot/utils/__init__.py
invana_bot/utils/config.py
invana_bot/utils/exceptions.py
invana_bot/utils/job.py
invana_bot/utils/selectors.py
invana_bot/utils/spiders.py
invana_bot/utils/storage.py
invana_bot/utils/url.py
invana_bot/validators/__init__.py
invana_bot/validators/manifest.py