Metadata-Version: 1.0
Name: invana-bot
Version: 0.1.36
Summary: A web spider framework that can transform websites into datasets with Crawl, Transform and Index workflow.
Home-page: https://github.com/invanalabs/invana-bot
Author: Ravi Raja Merugu
Author-email: ravi@invanalabs.ai
License: UNKNOWN
Platform: UNKNOWN
